build/lib/build/lib/build/lib/build/lib/mail_flagger/plugins/mt940.py
build/lib/build/lib/build/lib/mail_flagger/plugins/mt940.py
build/lib/build/lib/build/lib/mailflagger/plugins/mt940.py
build/lib/build/lib/mail_flagger/plugins/mt940.py
build/lib/build/lib/mailflagger/plugins/mt940.py
build/lib/mail_flagger/plugins/mt940.py
build/lib/mailflagger/plugins/mt940.py
mail_flagger/plugins/mt940.py
mailflagger/plugins/mt940.py
mailflagger_banking-0.1.0.dist-info/METADATA
mailflagger_banking-0.1.0.dist-info/WHEEL
mailflagger_banking-0.1.0.dist-info/entry_points.txt
mailflagger_banking-0.1.0.dist-info/top_level.txt
mailflagger_banking-0.1.0.dist-info/RECORD
